met_annot_unifier/__init__.py
met_annot_unifier/__main__.py
met_annot_unifier/cli.py
met_annot_unifier/exceptions.py
met_annot_unifier/foo.py
met_annot_unifier/aligner/__init__.py
met_annot_unifier/aligner/aligner.py
met_annot_unifier/aligner/parser.py
met_annot_unifier/aligner/utils.py
met_annot_unifier/config/column_config.json
met_annot_unifier-0.1.0.dist-info/METADATA
met_annot_unifier-0.1.0.dist-info/WHEEL
met_annot_unifier-0.1.0.dist-info/entry_points.txt
met_annot_unifier-0.1.0.dist-info/licenses/LICENSE
met_annot_unifier-0.1.0.dist-info/RECORD
