Metadata-Version: 2.4
Name: met-annot-unifier
Version: 0.1.0
Summary: A Python project to combine tabular outputs from GNPS, Sirius and ISDB
Project-URL: Homepage, https://mapp-metabolomics-unit.github.io/met-annot-unifier/
Project-URL: Repository, https://github.com/mapp-metabolomics-unit/met-annot-unifier
Project-URL: Documentation, https://mapp-metabolomics-unit.github.io/met-annot-unifier/
Author-email: Pierre-Marie Allard <pierre-marie.allard@unifr.ch>
License-File: LICENSE
Keywords: python
Classifier: Intended Audience :: Developers
Classifier: Programming Language :: Python
Classifier: Programming Language :: Python :: 3
Classifier: Programming Language :: Python :: 3.9
Classifier: Programming Language :: Python :: 3.10
Classifier: Programming Language :: Python :: 3.11
Classifier: Programming Language :: Python :: 3.12
Classifier: Programming Language :: Python :: 3.13
Classifier: Topic :: Software Development :: Libraries :: Python Modules
Requires-Python: <4.0,>=3.10
Requires-Dist: click>=8.1.8
Requires-Dist: ipykernel>=6.29.5
Requires-Dist: pandas-stubs>=2.2.2.240807
Requires-Dist: pandas>=2.2.3
